{
  "user": [
    {
      "pass": "d338b3f0f405eb5e51c8cc1e5ca66f02",
      "devices": [
        ""
      ],
      "online": true,
      "login": "Admin",
      "fio": "Слива М.В.",
      "status": "Admin"
    },
    {
      "pass": "",
      "devices": [],
      "online": false,
      "login": "user",
      "fio": "Some User",
      "status": "User"
    },
    {
      "pass": "bcbe3365e6ac95ea2c0343a2395834dd",
      "devices": [],
      "online": false,
      "login": "user2",
      "fio": "Иванов Иван Иванович",
      "email": "mail@mail.ru",
      "status": "User"
    },
    {
      "pass": "310dcbbf4cce62f762a2aaa148d556bd",
      "devices": [],
      "online": false,
      "login": "user3",
      "fio": "Иванов Иван Иванович3",
      "email": "mail3@mail.ru",
      "status": "User"
    },
    {
      "pass": "cb42e130d1471239a27fca6228094f0e",
      "online": false,
      "login": "userkkk",
      "fio": "kkk",
      "email": "kkk1@in.ru",
      "status": "User"
    }
  ]
}